{
  "hash": "155dd7f8",
  "configHash": "86c29611",
  "lockfileHash": "c7215efc",
  "browserHash": "c779fe9e",
  "optimized": {
    "lucide-react": {
      "src": "../../node_modules/lucide-react/dist/esm/lucide-react.mjs",
      "file": "lucide-react.js",
      "fileHash": "912f286a",
      "needsInterop": false
    },
    "marked": {
      "src": "../../node_modules/marked/lib/marked.esm.js",
      "file": "marked.js",
      "fileHash": "a2555e0f",
      "needsInterop": false
    },
    "react-dom": {
      "src": "../../node_modules/react-dom/index.js",
      "file": "react-dom.js",
      "fileHash": "41f49874",
      "needsInterop": true
    },
    "react-dom/client": {
      "src": "../../node_modules/react-dom/client.js",
      "file": "react-dom_client.js",
      "fileHash": "d4fd2d0f",
      "needsInterop": true
    },
    "react": {
      "src": "../../node_modules/react/index.js",
      "file": "react.js",
      "fileHash": "2dad9091",
      "needsInterop": true
    },
    "react/jsx-dev-runtime": {
      "src": "../../node_modules/react/jsx-dev-runtime.js",
      "file": "react_jsx-dev-runtime.js",
      "fileHash": "a3e79c56",
      "needsInterop": true
    },
    "react/jsx-runtime": {
      "src": "../../node_modules/react/jsx-runtime.js",
      "file": "react_jsx-runtime.js",
      "fileHash": "1924aa6f",
      "needsInterop": true
    },
    "zustand": {
      "src": "../../node_modules/zustand/esm/index.mjs",
      "file": "zustand.js",
      "fileHash": "d8d6a811",
      "needsInterop": false
    }
  },
  "chunks": {
    "react-CZunmVaX": {
      "file": "react-CZunmVaX.js",
      "isDynamicEntry": false
    }
  }
}